{
  "analysis_center": "IGS_COMBINED",
  "method": {
    "type": "phase_alignment_index",
    "formula": "cos(phase(CSD))"
  },
  "data_summary": {
    "total_pairs": 12841178,
    "files_processed": 910,
    "files_total": 910,
    "bins_used": 37,
    "distance_range_km": [
      70.26221526146985,
      12133.99368905904
    ],
    "coherence_range": [
      -0.12970006437093243,
      0.30920229089585477
    ],
    "mean_coherence": 0.0863352210265517
  },
  "model_comparison": {
    "models_tested": [
      "Exponential",
      "Gaussian",
      "Squared Exponential",
      "Power Law",
      "Power Law w/ Cutoff",
      "Mat\u00e9rn (\u03bd=1.5)",
      "Mat\u00e9rn (\u03bd=2.5)"
    ],
    "best_model_aic": "Mat\u00e9rn (\u03bd=1.5)",
    "model_results": [
      {
        "name": "Exponential",
        "aic": 114.2312013399666,
        "bic": 119.06395507789928,
        "r_squared": 0.9459929074503465,
        "delta_aic": 0.5034199742285779
      },
      {
        "name": "Gaussian",
        "aic": 123.28622433291807,
        "bic": 128.11897807085074,
        "r_squared": 0.9310179909210876,
        "delta_aic": 9.558442967180042
      },
      {
        "name": "Squared Exponential",
        "aic": 123.28622432852768,
        "bic": 128.11897806646036,
        "r_squared": 0.931017990929273,
        "delta_aic": 9.558442962789655
      },
      {
        "name": "Power Law",
        "aic": 222.22087754859749,
        "bic": 227.05363128653016,
        "r_squared": 0.0,
        "delta_aic": 108.49309618285946
      },
      {
        "name": "Power Law w/ Cutoff",
        "aic": 121.500995047209,
        "bic": 127.9446666977859,
        "r_squared": 0.9377261099015026,
        "delta_aic": 7.773213681470978
      },
      {
        "name": "Mat\u00e9rn (\u03bd=1.5)",
        "aic": 113.72778136573802,
        "bic": 118.5605351036707,
        "r_squared": 0.9467227486458955,
        "delta_aic": 0.0
      },
      {
        "name": "Mat\u00e9rn (\u03bd=2.5)",
        "aic": 115.83875268084216,
        "bic": 120.67150641877484,
        "r_squared": 0.9435947231674238,
        "delta_aic": 2.1109713151041376
      }
    ]
  },
  "best_fit": {
    "model_name": "Mat\u00e9rn (\u03bd=1.5)",
    "amplitude": 0.15199899064335634,
    "amplitude_error": 0.007016740708567914,
    "lambda_km": 3427.469776278241,
    "lambda_error": 237.96699955976857,
    "offset": -0.013354404869437177,
    "offset_error": 0.0030028354445401748,
    "r_squared": 0.9467227486458955,
    "n_bins": 37
  },
  "exponential_fit": {
    "model": "C(r) = A * exp(-r/lambda) + C0",
    "amplitude": 0.19384214417180962,
    "amplitude_error": 0.009185041296697885,
    "lambda_km": 3810.57196821923,
    "lambda_error": 414.58144297285384,
    "offset": -0.02165959850690071,
    "offset_error": 0.004812923435555527,
    "r_squared": 0.9459929074503465,
    "n_bins": 37
  },
  "tep_interpretation": {
    "tep_consistent": true,
    "correlation_length_assessment": "TEP-consistent",
    "signal_strength": "Strong",
    "best_model_vs_exponential": "Best model: Mat\u00e9rn (\u03bd=1.5) (\u0394AIC = -0.50)"
  }
}